cachecontrol/__init__.py
cachecontrol/_cmd.py
cachecontrol/adapter.py
cachecontrol/cache.py
cachecontrol/controller.py
cachecontrol/filewrapper.py
cachecontrol/heuristics.py
cachecontrol/py.typed
cachecontrol/serialize.py
cachecontrol/wrapper.py
cachecontrol/caches/__init__.py
cachecontrol/caches/file_cache.py
cachecontrol/caches/redis_cache.py
CacheControl-0.13.0.dist-info/LICENSE.txt
CacheControl-0.13.0.dist-info/METADATA
CacheControl-0.13.0.dist-info/WHEEL
CacheControl-0.13.0.dist-info/entry_points.txt
CacheControl-0.13.0.dist-info/top_level.txt
CacheControl-0.13.0.dist-info/RECORD
