Metadata-Version: 2.1
Name: CacheControl
Version: 0.13.0
Summary: httplib2 caching for requests
Home-page: https://github.com/ionrock/cachecontrol
Author: Eric Larson
Author-email: eric@ionrock.org
Keywords: requests http caching web
Classifier: Development Status :: 4 - Beta
Classifier: Environment :: Web Environment
Classifier: License :: OSI Approved :: Apache Software License
Classifier: Operating System :: OS Independent
Classifier: Programming Language :: Python :: 3.6
Classifier: Programming Language :: Python :: 3.7
Classifier: Programming Language :: Python :: 3.8
Classifier: Programming Language :: Python :: 3.9
Classifier: Programming Language :: Python :: 3.10
Classifier: Topic :: Internet :: WWW/HTTP
Requires-Python: >=3.6
Provides-Extra: filecache
Provides-Extra: redis
License-File: LICENSE.txt
